MyPeople.py
RustyWarePeople-0.0.1.dist-info/METADATA
RustyWarePeople-0.0.1.dist-info/WHEEL
RustyWarePeople-0.0.1.dist-info/top_level.txt
RustyWarePeople-0.0.1.dist-info/RECORD
