Metadata-Version: 2.1
Name: RustyWarePeople
Version: 0.0.1
Summary: Some people to extract
Home-page: UNKNOWN
License: UNKNOWN
Platform: UNKNOWN
Classifier: Programming Language :: Python :: 3
Classifier: Programming Language :: Python :: 3.6
Classifier: Programming Language :: Python :: 3.7
